odoo/addons/mrp_bom_responsible/README.rst
odoo/addons/mrp_bom_responsible/__init__.py
odoo/addons/mrp_bom_responsible/__manifest__.py
odoo/addons/mrp_bom_responsible/i18n/es.po
odoo/addons/mrp_bom_responsible/i18n/it.po
odoo/addons/mrp_bom_responsible/i18n/mrp_bom_responsible.pot
odoo/addons/mrp_bom_responsible/models/__init__.py
odoo/addons/mrp_bom_responsible/models/mrp_bom.py
odoo/addons/mrp_bom_responsible/models/mrp_production.py
odoo/addons/mrp_bom_responsible/readme/CONTRIBUTORS.rst
odoo/addons/mrp_bom_responsible/readme/DESCRIPTION.rst
odoo/addons/mrp_bom_responsible/static/description/icon.png
odoo/addons/mrp_bom_responsible/static/description/index.html
odoo/addons/mrp_bom_responsible/views/mrp_bom_views.xml
odoo14_addon_mrp_bom_responsible-14.0.1.0.1.dev7.dist-info/METADATA
odoo14_addon_mrp_bom_responsible-14.0.1.0.1.dev7.dist-info/WHEEL
odoo14_addon_mrp_bom_responsible-14.0.1.0.1.dev7.dist-info/top_level.txt
odoo14_addon_mrp_bom_responsible-14.0.1.0.1.dev7.dist-info/RECORD
